{
  "task": [
    {
      "name": "Alice",
      "completedTasks": 25
    },
    {
      "name": "Bob",
      "completedTasks": 18
    },
    {
      "name": "Charlie",
      "completedTasks": 22
    },
    {
      "name": "David",
      "completedTasks": 16
    },
    {
      "name": "Eve",
      "completedTasks": 19
    },
    {
      "name": "Frank",
      "completedTasks": 14
    },
    {
      "name": "Grace",
      "completedTasks": 20
    },
    {
      "name": "Heidi",
      "completedTasks": 17
    },
    {
      "name": "Ivan",
      "completedTasks": 21
    },
    {
      "name": "Judy",
      "completedTasks": 23
    }
  ]
  ,
   "message": [
    {
      "sender": "Alice",
      "messageCount": 15
    },
    {
      "sender": "Bob",
      "messageCount": 12
    },
    {
      "sender": "Charlie",
      "messageCount": 18
    },
    {
      "sender": "David",
      "messageCount": 10
    },
    {
      "sender": "Eve",
      "messageCount": 14
    },
    {
      "sender": "Frank",
      "messageCount": 8
    },
    {
      "sender": "Grace",
      "messageCount": 16
    },
    {
      "sender": "Heidi",
      "messageCount": 11
    },
    {
      "sender": "Ivan",
      "messageCount": 13
    },
    {
      "sender": "Judy",
      "messageCount": 17
    }
  ]
  ,
  "search": [
    {
      "searcher": "Alice",
      "resultsCount": 23000
    },
    {
      "searcher": "Bob",
      "resultsCount": 18000
    },
    {
      "searcher": "Charlie",
      "resultsCount": 35000
    },
    {
      "searcher": "David",
      "resultsCount": 27000
    },
    {
      "searcher": "Eve",
      "resultsCount": 22000
    },
    {
      "searcher": "Frank",
      "resultsCount": 14000
    },
    {
      "searcher": "Grace",
      "resultsCount": 29000
    },
    {
      "searcher": "Heidi",
      "resultsCount": 25000
    },
    {
      "searcher": "Ivan",
      "resultsCount": 21000
    },
    {
      "searcher": "Judy",
      "resultsCount": 12000
    }
  ]
}
